<?xml version="1.0" encoding="utf-8"?><!DOCTYPE Statute PUBLIC "-//Justice Canada//DTD Statute v2.0.0//EN" "Dtd/Version_2.0.0/Statute/Statute.dtd"><Statute bill-origin="commons" bill-type="govt-public" xml:lang="en" in-force="yes"><Identification><LongTitle>An Act to provide in the Province of Ontario for the annulment of marriage</LongTitle><ShortTitle status="official">Annulment of Marriages Act (Ontario)</ShortTitle><RunningHead>Annulment of Marriages</RunningHead><BillHistory><Stages stage="consolidation"><Date><YYYY>2016</YYYY><MM>06</MM><DD>22</DD></Date></Stages></BillHistory><Chapter><ConsolidatedNumber official="no">A-11.4</ConsolidatedNumber><AnnualStatuteId revised-statute="yes"><AnnualStatuteNumber>A-14</AnnualStatuteNumber><YYYY>1970</YYYY></AnnualStatuteId></Chapter></Identification><Body><Section><MarginalNote>Short title</MarginalNote><Label>1</Label><Text>This Act may be cited as the <XRefExternal reference-type="act">Annulment of Marriages Act (Ontario)</XRefExternal>.</Text><HistoricalNote>R.S., 1952, c. 85, s. 1; 1967-68, c. 24, s. 26.</HistoricalNote></Section><Section><MarginalNote>Part of law of England, on 15th July 1870 continued as law of Ontario</MarginalNote><Label>2</Label><Text>The law of England as to the annulment of marriage, as that law existed on the 15th day of July 1870, in so far as it can be made to apply in the Province of Ontario, and in so far as it has not been repealed, as to the Province, by any Act of the Parliament of the United Kingdom or by any Act of the Parliament of Canada or by this Act, and as altered, varied, modified or affected, as to the Province, by any such Act, is in force in the Province of Ontario.</Text><HistoricalNote>R.S., 1952, c. 85, s. 2; 1967-68, c. 24, s. 26.</HistoricalNote></Section><Section><MarginalNote>Jurisdiction</MarginalNote><Label>3</Label><Text>The Supreme Court of Ontario has jurisdiction for all purposes of this Act.</Text><HistoricalNote>R.S., 1952, c. 85, s. 3.</HistoricalNote></Section></Body></Statute>