<?xml version="1.0" encoding="utf-8"?><!--ArborText, Inc., 1988-2002, v.4002--><!DOCTYPE Statute PUBLIC "-//Justice Canada//DTD Statute v2.0.0//EN" "Dtd/Version_2.0.0/Statute/Statute.dtd"><Statute bill-origin="commons" bill-type="govt-public" xml:lang="en" in-force="yes"><Identification><BillNumber>C–459</BillNumber><Parliament><Session>2</Session><Number>37</Number><RegnalYear><Year-s>51-523</Year-s><Monarch>Elizabeth II</Monarch></RegnalYear><Year-s>2003</Year-s></Parliament><LongTitle>An Act to establish Holocaust Memorial Day</LongTitle><ShortTitle status="official">Holocaust Memorial Day Act</ShortTitle><RunningHead>Holocaust Memorial Day</RunningHead><BillHistory><Stages stage="consolidation"><Date><YYYY>2016</YYYY><MM>06</MM><DD>22</DD></Date></Stages><Stages stage="assented-to"><Date><YYYY>2003</YYYY><MM>11</MM><DD>7</DD></Date></Stages></BillHistory><Chapter><ConsolidatedNumber official="no">H-5.4</ConsolidatedNumber><AnnualStatuteId revised-statute="no"><AnnualStatuteNumber>24</AnnualStatuteNumber><YYYY>2003</YYYY></AnnualStatuteId></Chapter></Identification><Introduction><Preamble salutation="no"><Provision format-ref="indent-0-0" list-item="no" language-align="no"><MarginalNote>Preamble</MarginalNote><Text>WHEREAS the Holocaust refers to a specific event in history, namely, the deliberate and planned state-sponsored persecution and annihilation of European Jewry by the Nazis and their collaborators between 1933 and 1945;</Text></Provision><Provision format-ref="indent-0-0" list-item="no" language-align="no"><Text>WHEREAS six million Jewish men, women and children perished under this policy of hatred and genocide;</Text></Provision><Provision format-ref="indent-0-0" list-item="no" language-align="no"><Text>WHEREAS millions of others were victims of that policy because of their physical or mental disabilities, race, religion or sexual orientation;</Text></Provision><Provision format-ref="indent-0-0" list-item="no" language-align="no"><Text>WHEREAS the terrible destruction and pain of the Holocaust must never be forgotten;</Text></Provision><Provision format-ref="indent-0-0" list-item="no" language-align="no"><Text>WHEREAS systematic violence, genocide, persecution, racism and hatred continue to occur throughout the world;</Text></Provision><Provision format-ref="indent-0-0" list-item="no" language-align="no"><Text>WHEREAS the Parliament of Canada is committed to using legislation, education and example to protect Canadians from violence, racism and hatred and to stopping those who foster or commit crimes of violence, racism and hatred;</Text></Provision><Provision format-ref="indent-0-0" list-item="no" language-align="no"><Text>AND WHEREAS Yom ha-Shoah or the Day of the Holocaust, as determined in each year by the Jewish lunar calendar, is an opportune day to reflect on and educate about the enduring lessons of the Holocaust and to reaffirm a commitment to uphold human rights;</Text></Provision></Preamble><Enacts><Provision format-ref="indent-0-0" list-item="no" language-align="yes"><Text>NOW, THEREFORE, Her Majesty, by and with the advice and consent of the Senate and House of Commons of Canada, enacts as follows:</Text></Provision></Enacts></Introduction><Body><Heading level="1"><TitleText>Short Title</TitleText></Heading><Section><MarginalNote>Short title</MarginalNote><Label>1</Label><Text>This Act may be cited as the <XRefExternal reference-type="act">Holocaust Memorial Day Act</XRefExternal>.</Text></Section><Heading level="1"><TitleText>Holocaust Memorial Day</TitleText></Heading><Section><MarginalNote>Holocaust Memorial Day — Yom ha-Shoah</MarginalNote><Label>2</Label><Text>Yom ha-Shoah or the Day of the Holocaust, as determined in each year by the Jewish lunar calendar, is proclaimed as “Holocaust Memorial Day — Yom ha-Shoah”.</Text></Section></Body></Statute>